.gitignore
CHANGES.txt
CONTRIBUTORS.txt
MANIFEST.in
README.rst
setup.py
docs/LICENSE.GPL
docs/LICENSE.txt
docs/MANUAL.txt
src/raptus/__init__.py
src/raptus.article.slideshow.egg-info/PKG-INFO
src/raptus.article.slideshow.egg-info/SOURCES.txt
src/raptus.article.slideshow.egg-info/dependency_links.txt
src/raptus.article.slideshow.egg-info/entry_points.txt
src/raptus.article.slideshow.egg-info/namespace_packages.txt
src/raptus.article.slideshow.egg-info/not-zip-safe
src/raptus.article.slideshow.egg-info/requires.txt
src/raptus.article.slideshow.egg-info/top_level.txt
src/raptus/article/__init__.py
src/raptus/article/slideshow/__init__.py
src/raptus/article/slideshow/configure.zcml
src/raptus/article/slideshow/setuphandlers.py
src/raptus/article/slideshow/browser/__init__.py
src/raptus/article/slideshow/browser/configure.zcml
src/raptus/article/slideshow/browser/slideshow.gif
src/raptus/article/slideshow/browser/slideshow.js
src/raptus/article/slideshow/browser/slideshow.pt
src/raptus/article/slideshow/browser/slideshow.py
src/raptus/article/slideshow/i18n/raptus.article-de.mo
src/raptus/article/slideshow/i18n/raptus.article-de.po
src/raptus/article/slideshow/i18n/raptus.article-fr.mo
src/raptus/article/slideshow/i18n/raptus.article-fr.po
src/raptus/article/slideshow/i18n/raptus.article.pot
src/raptus/article/slideshow/profiles/default/cssregistry.xml
src/raptus/article/slideshow/profiles/default/jsregistry.xml
src/raptus/article/slideshow/profiles/default/metadata.xml
src/raptus/article/slideshow/profiles/default/propertiestool.xml
src/raptus/article/slideshow/profiles/default/raptus.article.slideshow_install.txt
src/raptus/article/slideshow/profiles/default/skins.xml
src/raptus/article/slideshow/profiles/default/viewlets.xml
src/raptus/article/slideshow/skins/raptus_article_slideshow/raptus.article.slideshow.css.dtml