Metadata-Version: 1.1
Name: raptus.article.slideshow
Version: 1.0a1
Summary: Provides a responsive image slideshow component
Home-page: http://github.com/Raptus/raptus.article.slideshow
Author: Raptus AG
Author-email: dev@raptus.com
License: gpl
Platform: UNKNOWN
Classifier: Programming Language :: Python
